windtalker/__init__.py
windtalker/_version.py
windtalker/api.py
windtalker/asymmetric.py
windtalker/cipher.py
windtalker/exc.py
windtalker/files.py
windtalker/paths.py
windtalker/symmetric.py
windtalker/docs/__init__.py
windtalker/tests/__init__.py
windtalker/tests/helper.py
windtalker/tests/my-secret-file-decrypted.txt
windtalker/tests/my-secret-file-encrypted.txt
windtalker/tests/my-secret-file.txt
windtalker/vendor/__init__.py
windtalker/vendor/hashes.py
windtalker/vendor/pytest_cov_helper.py
windtalker-1.0.1.dist-info/AUTHORS.rst
windtalker-1.0.1.dist-info/LICENSE.txt
windtalker-1.0.1.dist-info/METADATA
windtalker-1.0.1.dist-info/WHEEL
windtalker-1.0.1.dist-info/top_level.txt
windtalker-1.0.1.dist-info/RECORD
